jira_freeplane/__init__.py
jira_freeplane/common.py
jira_freeplane/libjira.py
jira_freeplane/mm.py
jira_freeplane/mm_settings.py
jira_freeplane/runtime.py
jira_freeplane-1.0.10.dist-info/entry_points.txt
jira_freeplane-1.0.10.dist-info/LICENSE.txt
jira_freeplane-1.0.10.dist-info/WHEEL
jira_freeplane-1.0.10.dist-info/METADATA
jira_freeplane-1.0.10.dist-info/RECORD
